strawberry_jwt_auth/__init__.py
strawberry_jwt_auth/auth_settings.py
strawberry_jwt_auth/decorator.py
strawberry_jwt_auth/extension.py
strawberry_jwt_auth/jwt_generator.py
strawberry_jwt_auth/models.py
strawberry_jwt_auth/views.py
strawberry_jwt_auth/migrations/0001_initial.py
strawberry_jwt_auth/migrations/__init__.py
strawberry_jwt_auth/utils/__init__.py
strawberry_jwt_auth/utils/authentication.py
strawberry_jwt_auth-0.2.2.dist-info/METADATA
strawberry_jwt_auth-0.2.2.dist-info/WHEEL
strawberry_jwt_auth-0.2.2.dist-info/top_level.txt
strawberry_jwt_auth-0.2.2.dist-info/RECORD
