Metadata-Version: 2.1
Name: strawberry-jwt-auth
Version: 0.2.2
Summary: A JWT auth library based on Django and strawberry
Author: grvsh02 (Gaurav Sharma)
Author-email: <gaurav021201@gmail.com>
Keywords: python,jwt,auth,strawberry,graphql,Authentication
Classifier: Development Status :: 3 - Alpha
Classifier: Intended Audience :: Developers
Classifier: Programming Language :: Python :: 3
Classifier: Operating System :: Unix
Classifier: Operating System :: MacOS :: MacOS X
Classifier: Operating System :: Microsoft :: Windows
Requires-Dist: pyjwt
Requires-Dist: strawberry-graphql
Requires-Dist: django
Requires-Dist: phonenumbers
